lorikeet/__init__.py
lorikeet/api_serializers.py
lorikeet/api_views.py
lorikeet/api_views_test.py
lorikeet/api_views_test_adjustment.py
lorikeet/api_views_test_cart_items.py
lorikeet/api_views_test_checkout.py
lorikeet/api_views_test_delivery_addresses.py
lorikeet/api_views_test_payment_method.py
lorikeet/apps.py
lorikeet/cart_checkers.py
lorikeet/conftest.py
lorikeet/exceptions.py
lorikeet/exceptions_test.py
lorikeet/extras/__init__.py
lorikeet/extras/email_invoice/__init__.py
lorikeet/extras/email_invoice/apps.py
lorikeet/extras/email_invoice/settings.py
lorikeet/extras/email_invoice/signal_handlers.py
lorikeet/extras/email_invoice/signal_handlers_test.py
lorikeet/extras/email_invoice/textify.py
lorikeet/extras/starshipit/__init__.py
lorikeet/extras/starshipit/migrations/0001_initial.py
lorikeet/extras/starshipit/migrations/__init__.py
lorikeet/extras/starshipit/models.py
lorikeet/extras/starshipit/submit.py
lorikeet/extras/starshipit/tasks.py
lorikeet/extras/stripe/__init__.py
lorikeet/extras/stripe/api_serializers.py
lorikeet/extras/stripe/migrations/0001_initial.py
lorikeet/extras/stripe/migrations/0002_stripepayment.py
lorikeet/extras/stripe/migrations/0003_auto_20170502_1043.py
lorikeet/extras/stripe/migrations/0004_auto_20170502_1228.py
lorikeet/extras/stripe/migrations/__init__.py
lorikeet/extras/stripe/models.py
lorikeet/extras/stripe/tests.py
lorikeet/generic_views.py
lorikeet/middleware.py
lorikeet/migrations/0001_initial.py
lorikeet/migrations/0002_auto_20161213_1158.py
lorikeet/migrations/0003_auto_20161220_1313.py
lorikeet/migrations/0004_auto_20161220_1431.py
lorikeet/migrations/0005_cart_payment_method.py
lorikeet/migrations/0006_paymentmethod_active.py
lorikeet/migrations/0007_deliveryaddress_active.py
lorikeet/migrations/0008_auto_20170117_0453.py
lorikeet/migrations/0009_auto_20170306_1150.py
lorikeet/migrations/0010_order_grand_total.py
lorikeet/migrations/0011_lineitem_total_when_charged.py
lorikeet/migrations/0012_cart_email.py
lorikeet-0.2.2.dist-info/LICENSE
lorikeet-0.2.2.dist-info/WHEEL
lorikeet-0.2.2.dist-info/METADATA
lorikeet-0.2.2.dist-info/RECORD
