Metadata-Version: 2.1
Name: lorikeet
Version: 0.2.2
Summary: A simple, generic, API-only shopping cart framework for Django
Home-page: https://lorikeet.readthedocs.io/
License: MIT
Author: Leigh Brenecki
Author-email: leigh@brenecki.id.au
Requires-Python: >=3.5
Classifier: License :: OSI Approved :: MIT License
Classifier: Programming Language :: Python :: 3
Classifier: Programming Language :: Python :: 3.5
Classifier: Programming Language :: Python :: 3.6
Classifier: Programming Language :: Python :: 3.7
Classifier: Programming Language :: Python :: 3.8
Provides-Extra: email_invoice
Provides-Extra: starshipit
Provides-Extra: stripe
Requires-Dist: django (>=2.2,<4)
Requires-Dist: django-model-utils (>=4.0.0,<5.0.0)
Requires-Dist: djangorestframework (>=3.10,<4.0)
Requires-Dist: premailer (>=3.6,<4.0); extra == "email_invoice"
Requires-Dist: requests (>=2.21,<3.0); extra == "starshipit"
Requires-Dist: stripe (>=2.41,<3.0); extra == "stripe"
Project-URL: Repository, https://github.com/excitedleigh/lorikeet
